edc_appointment/__init__.py
edc_appointment/admin/__init__.py
edc_appointment/admin/actions.py
edc_appointment/admin/appointment_admin.py
edc_appointment/admin/list_filters.py
edc_appointment/admin_site.py
edc_appointment/analytics/__init__.py
edc_appointment/analytics/dataframes/__init__.py
edc_appointment/analytics/dataframes/get_appointment_df.py
edc_appointment/appointment_reason_updater.py
edc_appointment/appointment_status_updater.py
edc_appointment/apps.py
edc_appointment/auth_objects.py
edc_appointment/auths.py
edc_appointment/choices.py
edc_appointment/constants.py
edc_appointment/context_processors.py
edc_appointment/creators/__init__.py
edc_appointment/creators/appointment_creator.py
edc_appointment/creators/appointments_creator.py
edc_appointment/creators/unscheduled_appointment_creator.py
edc_appointment/creators/utils.py
edc_appointment/exceptions.py
edc_appointment/form_runners.py
edc_appointment/form_validator_mixins/__init__.py
edc_appointment/form_validator_mixins/next_appointment_crf_form_validator_mixin.py
edc_appointment/form_validator_mixins/window_period_form_validator_mixin.py
edc_appointment/form_validators/__init__.py
edc_appointment/form_validators/appointment_form_validator.py
edc_appointment/form_validators/next_appointment_crf_form_validator.py
edc_appointment/form_validators/utils.py
edc_appointment/forms/__init__.py
edc_appointment/forms/appointment_form.py
edc_appointment/list_data.py
edc_appointment/management/__init__.py
edc_appointment/management/commands/__init__.py
edc_appointment/management/commands/close_appointments.py
edc_appointment/management/commands/reset_visit_code_sequences.py
edc_appointment/management/commands/update_appointment_status.py
edc_appointment/management/commands/update_skipped_appointments.py
edc_appointment/managers.py
edc_appointment/migrations/0001_initial.py
edc_appointment/migrations/0002_auto_20161126_1156.py
edc_appointment/migrations/0003_auto_20161127_2226.py
edc_appointment-1.1.2.dist-info/licenses/LICENSE
edc_appointment-1.1.2.dist-info/WHEEL
edc_appointment-1.1.2.dist-info/METADATA
edc_appointment-1.1.2.dist-info/RECORD
